{
  "type": "solarsystem:space",
  "generator": {
    "type": "minecraft:noise",
    "seed": 2734166642,
    "settings": "solarsystem:io",
    "biome_source": {
      "type": "minecraft:multi_noise",
      "biomes": [
        {
          "biome": "solarsystem:ionian_mountains",
          "parameters": {
            "temperature": 0,
            "humidity": 0,
            "continentalness": 0.5,
            "erosion": 0,
            "weirdness": 0,
            "depth": 0,
            "offset": 0
          }
        },
        {
          "biome": "solarsystem:ionian_hills",
          "parameters": {
            "temperature": 0,
            "humidity": 0,
            "continentalness": 0.3,
            "erosion": 0,
            "weirdness": 0,
            "depth": 0,
            "offset": 0
          }
        },
        {
          "biome": "solarsystem:ionian_plains",
          "parameters": {
            "temperature": 0,
            "humidity": 0,
            "continentalness": 0.2,
            "erosion": 0,
            "weirdness": 0,
            "depth": 0,
            "offset": 0
          }
        },
        {
          "biome": "solarsystem:ionian_valley",
          "parameters": {
            "temperature": 0,
            "humidity": 0,
            "continentalness": -0.2,
            "erosion": 0,
            "weirdness": 0,
            "depth": 0,
            "offset": 0
          }
        },
        {
          "biome": "solarsystem:ionian_lava_flow",
          "parameters": {
            "temperature": 0,
            "humidity": 0,
            "continentalness": 0,
            "erosion": 0,
            "weirdness": 0,
            "depth": 0,
            "offset": 0.19
          }
        },
        {
          "biome": "solarsystem:ionian_volcano",
          "parameters": {
            "temperature": 0,
            "humidity": 0.7,
            "continentalness": 0,
            "erosion": 0,
            "weirdness": 0,
            "depth": 0,
            "offset": 0.4
          }
        }
      ]
    }
  }
}
